validdict/__init__.py
validdict/validator.py
pyvaliddict_rj-1.0.0.dist-info/METADATA
pyvaliddict_rj-1.0.0.dist-info/WHEEL
pyvaliddict_rj-1.0.0.dist-info/RECORD
